aophelper/__init__.py
aophelper/aspect.py
aophelper/baseAdvice.py
aophelper/decorators.py
aophelper-0.6.0.dist-info/LICENSE
aophelper-0.6.0.dist-info/METADATA
aophelper-0.6.0.dist-info/WHEEL
aophelper-0.6.0.dist-info/top_level.txt
aophelper-0.6.0.dist-info/RECORD
