Metadata-Version: 2.1
Name: aophelper
Version: 0.6.0
Summary: AOP (Aspect-Oriented Programming) helper for Python
Home-page: https://github.com/mathbook3948/AOPHelper
Author: mathbook3948
Author-email: yuno.jung.07@gmail.com
Classifier: Programming Language :: Python :: 3
Classifier: License :: OSI Approved :: MIT License
Classifier: Operating System :: OS Independent
Requires-Python: >=3.6
License-File: LICENSE
